theproofistrivial/__init__.py
theproofistrivial/__main__.py
theproofistrivial-0.1.2.dist-info/LICENSE
theproofistrivial-0.1.2.dist-info/METADATA
theproofistrivial-0.1.2.dist-info/WHEEL
theproofistrivial-0.1.2.dist-info/entry_points.txt
theproofistrivial-0.1.2.dist-info/top_level.txt
theproofistrivial-0.1.2.dist-info/RECORD
