Metadata-Version: 2.1
Name: theproofistrivial
Version: 0.1.2
Summary: Python port of TheProofIsTrivial
Home-page: https://github.com/ahmedkhalf/TheProofIsTrivial
Author: Ahmed Khalf
Author-email: ahmedkhalf567@gmail.com
License: UNKNOWN
Project-URL: Bug Tracker, https://github.com/ahmedkhalf/TheProofIsTrivial/issues
Platform: UNKNOWN
Classifier: Development Status :: 5 - Production/Stable
Classifier: Environment :: Console
Classifier: Intended Audience :: Education
Classifier: Intended Audience :: Science/Research
Classifier: Natural Language :: English
Classifier: Operating System :: OS Independent
Classifier: Topic :: Education
Classifier: Topic :: Games/Entertainment
Classifier: Topic :: Terminals
Classifier: Topic :: Text Processing
Classifier: Programming Language :: Python :: 3
Classifier: License :: OSI Approved :: MIT License
Requires-Python: >=3.6
License-File: LICENSE
